mustang/__init__.py
mustang/exceptions.py
mustang/commands/__init__.py
mustang/commands/base.py
mustang/commands/check.py
mustang/commands/command.py
mustang/commands/main.py
mustang/engine/__init__.py
mustang/engine/base.py
mustang/engine/sqlite.py
mustang/schema/__init__.py
mustang/schema/database.py
mustang/schema/field.py
mustang/schema/model.py
mustang/schema/schema.py
test/__init__.py
test/base.py
test/test_model.py
pymustang-0.1.dist-info/LICENSE
pymustang-0.1.dist-info/METADATA
pymustang-0.1.dist-info/WHEEL
pymustang-0.1.dist-info/entry_points.txt
pymustang-0.1.dist-info/top_level.txt
pymustang-0.1.dist-info/RECORD
