Metadata-Version: 2.1
Name: pymustang
Version: 0.1
Summary: A lightweight, Sqlite ORM in Python.
Home-page: https://github.com/vincent-lg/mustang/
Author: Vincent Le Goff
Author-email: vincent.legoff.srs@gmail.com
License: UNKNOWN
Platform: UNKNOWN
Classifier: Development Status :: 1 - Planning
Classifier: Intended Audience :: Developers
Classifier: License :: OSI Approved :: BSD License
Classifier: Operating System :: OS Independent
Classifier: Programming Language :: Python :: 3.6
Classifier: Programming Language :: Python :: 3.7
Classifier: Programming Language :: Python :: 3.8
Classifier: Programming Language :: Python :: 3.9
Requires-Python: >=3.6
